django_urr/__init__.py
django_urr/extract.py
django_urr/management/__init__.py
django_urr/management/commands/__init__.py
django_urr/management/commands/urr_list.py
django_urr-0.3.0.dist-info/METADATA
django_urr-0.3.0.dist-info/WHEEL
django_urr-0.3.0.dist-info/licenses/LICENSE
django_urr-0.3.0.dist-info/RECORD
