Metadata-Version: 2.1
Name: django-urr
Version: 0.3.0
Summary: URL resolver utilities for Django
Project-URL: Homepage, https://github.com/valohai/django-urr
Author-email: Valohai <info@valohai.com>
Maintainer-email: Aarni Koskela <akx@iki.fi>
License-Expression: MIT
License-File: LICENSE
Requires-Python: >=3.7
Requires-Dist: django
Provides-Extra: test
Requires-Dist: pytest-django; extra == 'test'
Requires-Dist: pytest>=6.0; extra == 'test'
